README.md
setup.py
mahmoud_pkg.egg-info/PKG-INFO
mahmoud_pkg.egg-info/SOURCES.txt
mahmoud_pkg.egg-info/dependency_links.txt
mahmoud_pkg.egg-info/top_level.txt
mahmoudpkg/__init__.py
mahmoudpkg/humans/__init__.py
mahmoudpkg/humans/driver.py
mahmoudpkg/humans/person.py
mahmoudpkg/vehicles/__init__.py
mahmoudpkg/vehicles/car.py
mahmoudpkg/vehicles/motorbike.py