Metadata-Version: 1.0
Name: mahmoud-pkg
Version: 1.0
Summary: Example package that ...
Home-page: UNKNOWN
Author: M S
Author-email: mxy2321@gmail.com
License: BSD
Platform: UNKNOWN
